PyScreenUtils/__init__.py
PyScreenUtils/cursor_util.py
PyScreenUtils/inputsafe_print.py
PyScreenUtils/screen_util.py
PyScreenUtils-0.1.0.dist-info/LICENSE
PyScreenUtils-0.1.0.dist-info/METADATA
PyScreenUtils-0.1.0.dist-info/WHEEL
PyScreenUtils-0.1.0.dist-info/top_level.txt
PyScreenUtils-0.1.0.dist-info/RECORD
