Metadata-Version: 2.1
Name: PyScreenUtils
Version: 0.1.0
Summary: Terminal utils.
Home-page: https://github.com/KrisTHL181/PyScreenUtils
Author: KrisTHL181
Author-email: KrisTHL181@outlook.com
Classifier: Programming Language :: Python :: 3
Classifier: License :: OSI Approved :: MIT License
Classifier: Operating System :: OS Independent
Requires-Python: >=3.6
License-File: LICENSE
Requires-Dist: colorama
